{
  "success": true,
  "url": "https://www.codewars.com/api/v1/code-challenges/5945ec680c9fb93d87000197",
  "data": {
    "id": "5945ec680c9fb93d87000197",
    "name": "Quadratics Fun",
    "slug": "quadratics-fun",
    "category": "reference",
    "publishedAt": "2017-06-18T02:58:49.247Z",
    "approvedAt": null,
    "languages": [
      "python"
    ],
    "url": "https://www.codewars.com/kata/5945ec680c9fb93d87000197",
    "rank": {
      "id": null,
      "name": null,
      "color": null
    },
    "createdAt": "2017-06-18T02:58:53.399Z",
    "createdBy": {
      "username": "parks6",
      "url": "https://www.codewars.com/users/parks6"
    },
    "description": "Your job is to write a function ```quadratic``` that takes the values of ```a```, ```b``` and ```c``` for a quadratic equation a^2+bx+c=0, and returns the value(s) of x that satisfies that equation.\n\nIf there is no real solution, return the string ```'No real solution'```.\nIf there is one real solution, just return that one solution.\nIf there are two real solutions, return a list of the two solutions, sorted from smallest to largest.\n\nRound all solutions to 1 decimal place.\n\nExamples:\n\n(1, -4, 4) --> 2\n\n(1, 5, 6) --> [-2, -3]\n\n(2, 4, 3) --> 'No real solution'\n",
    "totalAttempts": 122,
    "totalCompleted": 31,
    "totalStars": 0,
    "voteScore": 33,
    "tags": [
      "Mathematics",
      "Algebra"
    ],
    "contributorsWanted": false,
    "unresolved": {
      "issues": 3,
      "suggestions": 0
    }
  },
  "error": null,
  "isValid": false,
  "validationErrors": [
    {
      "path": "approvedBy",
      "message": "Required field 'approvedBy' is missing"
    },
    {
      "path": "rank.id",
      "message": "Expected integer, got object (not integer)"
    },
    {
      "path": "rank.name",
      "message": "Expected type 'string', got 'object'"
    },
    {
      "path": "rank.color",
      "message": "Expected type 'string', got 'object'"
    },
    {
      "path": "approvedBy",
      "message": "Required field 'approvedBy' is missing"
    },
    {
      "path": "approvedAt",
      "message": "Expected type 'string', got 'object'"
    }
  ]
}