{
  "id": "52a401f1a65172ce8f00008d",
  "name": "Touchdown?",
  "slug": "touchdown",
  "category": "algorithms",
  "publishedAt": "2013-12-08T16:11:50.960Z",
  "approvedAt": "2019-10-29T23:54:49.090Z",
  "languages": [
    "javascript",
    "coffeescript",
    "python"
  ],
  "url": "https://www.codewars.com/kata/52a401f1a65172ce8f00008d",
  "rank": {
    "id": -4,
    "name": "4 kyu",
    "color": "blue"
  },
  "createdAt": "2013-12-08T05:21:53.114Z",
  "createdBy": {
    "username": "OverZealous",
    "url": "https://www.codewars.com/users/OverZealous"
  },
  "approvedBy": {
    "username": "Blind4Basics",
    "url": "https://www.codewars.com/users/Blind4Basics"
  },
  "totalAttempts": 953,
  "totalCompleted": 125,
  "totalStars": 40,
  "voteScore": 46,
  "tags": [
    "Algorithms"
  ],
  "contributorsWanted": true,
  "unresolved": {
    "issues": 0,
    "suggestions": 1
  }
}