{
  "id": "52f78966747862fc9a0009ae",
  "name": "Reverse polish notation calculator",
  "slug": "reverse-polish-notation-calculator",
  "category": "algorithms",
  "publishedAt": "2014-02-09T14:19:13.439Z",
  "approvedAt": "2014-02-24T17:45:51.329Z",
  "languages": [
    "javascript",
    "ruby",
    "python",
    "coffeescript",
    "haskell",
    "java",
    "csharp",
    "clojure",
    "php",
    "cobol",
    "julia",
    "typescript",
    "prolog"
  ],
  "url": "https://www.codewars.com/kata/52f78966747862fc9a0009ae",
  "rank": {
    "id": -6,
    "name": "6 kyu",
    "color": "yellow"
  },
  "createdAt": "2014-02-09T13:57:58.997Z",
  "createdBy": {
    "username": "vgrichina",
    "url": "https://www.codewars.com/users/vgrichina"
  },
  "approvedBy": {
    "username": "jhoffner",
    "url": "https://www.codewars.com/users/jhoffner"
  },
  "description": "Your job is to create a calculator which evaluates expressions in [Reverse Polish notation](http://en.wikipedia.org/wiki/Reverse_Polish_notation).\n\nFor example expression `5 1 2 + 4 * + 3 -` (which is equivalent to `5 + ((1 + 2) * 4) - 3` in normal notation) should evaluate to `14`.\n\nFor your convenience, the input is formatted such that a space is provided between every token.\n\nEmpty expression should evaluate to `0`.\n\nValid operations are `+`, `-`, `*`, `/`.\n\nYou may assume that there won't be exceptional situations (like stack underflow or division by zero).",
  "totalAttempts": 64138,
  "totalCompleted": 11843,
  "totalStars": 743,
  "voteScore": 1365,
  "tags": [
    "Algorithms",
    "Mathematics",
    "Interpreters",
    "Parsing",
    "Strings"
  ],
  "contributorsWanted": true,
  "unresolved": {
    "issues": 4,
    "suggestions": 1
  }
}