{
  "id": "5612a0d653d31f401b00001a",
  "name": "Regular Expressions Engine",
  "slug": "regular-expressions-engine",
  "category": "algorithms",
  "publishedAt": "2015-10-05T17:15:37.804Z",
  "approvedAt": null,
  "languages": [
    "javascript"
  ],
  "url": "https://www.codewars.com/kata/5612a0d653d31f401b00001a",
  "rank": {
    "id": null,
    "name": null,
    "color": null
  },
  "createdAt": "2015-10-05T16:09:59.253Z",
  "createdBy": {
    "username": "Freywar",
    "url": "https://www.codewars.com/users/Freywar"
  },
  "totalAttempts": 425,
  "totalCompleted": 17,
  "totalStars": 13,
  "voteScore": 8,
  "tags": [
    "Regular Expressions",
    "Algorithms"
  ],
  "contributorsWanted": true,
  "unresolved": {
    "issues": 2,
    "suggestions": 0
  }
}