{
  "id": "57613fb1033d766171000d60",
  "name": "UEFA EURO 2016",
  "slug": "uefa-euro-2016",
  "category": "reference",
  "publishedAt": "2016-06-15T12:24:31.084Z",
  "approvedAt": "2016-06-16T09:14:34.951Z",
  "languages": [
    "javascript",
    "ruby",
    "csharp",
    "python"
  ],
  "url": "https://www.codewars.com/kata/57613fb1033d766171000d60",
  "rank": {
    "id": -8,
    "name": "8 kyu",
    "color": "white"
  },
  "createdAt": "2016-06-15T11:44:49.460Z",
  "createdBy": {
    "username": "miagkovi",
    "url": "https://www.codewars.com/users/miagkovi"
  },
  "approvedBy": {
    "username": "smile67",
    "url": "https://www.codewars.com/users/smile67"
  },
  "totalAttempts": 24477,
  "totalCompleted": 12342,
  "totalStars": 115,
  "voteScore": 1528,
  "tags": [
    "Strings",
    "Arrays",
    "Fundamentals"
  ],
  "contributorsWanted": true,
  "unresolved": {
    "issues": 1,
    "suggestions": 1
  }
}