{
  "id": "57fece4108d102ea65000bf6",
  "name": "Practical Interview Prep: Binary Search Tree .push()",
  "slug": "practical-interview-prep-binary-search-tree-push",
  "category": "reference",
  "publishedAt": "2016-10-13T00:07:27.090Z",
  "approvedAt": null,
  "languages": [
    "javascript"
  ],
  "url": "https://www.codewars.com/kata/57fece4108d102ea65000bf6",
  "rank": {
    "id": null,
    "name": null,
    "color": null
  },
  "createdAt": "2016-10-12T23:58:57.771Z",
  "createdBy": {
    "username": "ish2f4f",
    "url": "https://www.codewars.com/users/ish2f4f"
  },
  "totalAttempts": 121,
  "totalCompleted": 34,
  "totalStars": 5,
  "voteScore": 27,
  "tags": [
    "Binary Search Trees",
    "Data Structures",
    "Algorithms",
    "Fundamentals"
  ],
  "contributorsWanted": true,
  "unresolved": {
    "issues": 2,
    "suggestions": 2
  }
}