{
  "id": "58aaa3ca821a767300000017",
  "name": "Simple Fun #150: Robot Transfer",
  "slug": "simple-fun-number-150-robot-transfer",
  "category": "games",
  "publishedAt": "2017-02-20T08:42:38.089Z",
  "approvedAt": "2017-03-13T03:24:28.988Z",
  "languages": [
    "javascript",
    "csharp",
    "python",
    "ruby",
    "haskell"
  ],
  "url": "https://www.codewars.com/kata/58aaa3ca821a767300000017",
  "rank": {
    "id": -6,
    "name": "6 kyu",
    "color": "yellow"
  },
  "createdAt": "2017-02-20T08:07:39.567Z",
  "createdBy": {
    "username": "myjinxin2015",
    "url": "https://www.codewars.com/users/myjinxin2015"
  },
  "approvedBy": {
    "username": "kazk",
    "url": "https://www.codewars.com/users/kazk"
  },
  "totalAttempts": 2081,
  "totalCompleted": 250,
  "totalStars": 17,
  "voteScore": 93,
  "tags": [
    "Puzzles"
  ],
  "contributorsWanted": true,
  "unresolved": {
    "issues": 0,
    "suggestions": 0
  }
}