{
  "id": "591cac98a6007e87d900013a",
  "name": "Change case",
  "slug": "change-case",
  "category": "reference",
  "publishedAt": "2017-05-18T12:53:51.981Z",
  "approvedAt": "2017-10-27T17:43:15.260Z",
  "languages": [
    "java"
  ],
  "url": "https://www.codewars.com/kata/591cac98a6007e87d900013a",
  "rank": {
    "id": -6,
    "name": "6 kyu",
    "color": "yellow"
  },
  "createdAt": "2017-05-17T20:03:36.552Z",
  "createdBy": {
    "username": "k.steflovic",
    "url": "https://www.codewars.com/users/k.steflovic"
  },
  "approvedBy": {
    "username": "ZED.CWT",
    "url": "https://www.codewars.com/users/ZED.CWT"
  },
  "totalAttempts": 1925,
  "totalCompleted": 91,
  "totalStars": 17,
  "voteScore": 33,
  "tags": [
    "Fundamentals"
  ],
  "contributorsWanted": false,
  "unresolved": {
    "issues": 0,
    "suggestions": 1
  }
}