{
  "id": "59884371d1d8d3d9270000a5",
  "name": "Nut Farm",
  "slug": "nut-farm",
  "category": "algorithms",
  "publishedAt": "2017-08-08T20:58:14.999Z",
  "approvedAt": "2017-08-10T07:31:27.180Z",
  "languages": [
    "java",
    "javascript",
    "csharp",
    "python",
    "dart",
    "lua"
  ],
  "url": "https://www.codewars.com/kata/59884371d1d8d3d9270000a5",
  "rank": {
    "id": -6,
    "name": "6 kyu",
    "color": "yellow"
  },
  "createdAt": "2017-08-07T10:39:45.162Z",
  "createdBy": {
    "username": "dinglemouse",
    "url": "https://www.codewars.com/users/dinglemouse"
  },
  "approvedBy": {
    "username": "Blind4Basics",
    "url": "https://www.codewars.com/users/Blind4Basics"
  },
  "description": "# Story\n\nIt's a pretty relaxing life here at the nut farm.\n\nMost of the time we just sit around looking at our nuts.\n\nBut once a year comes harvesting time...\n\nHarvesting nuts is very easy. We just shake the trees and the nuts fall out!\n\n---\n\nAs they fall down the nuts might hit branches:\n* Sometimes they bounce left.\n* Sometimes they bounce right.\n* Sometimes they get stuck in the tree and don't fall out at all.\n\n# Legend\n\n* ```o``` = a nut\n* ```\\``` = branch. A nut hitting this branch bounces right\n* ```/``` = branch. A nut hitting this branch bounces left\n* ```_``` = branch. A nut hitting this branch gets stuck in the tree\n* ```.``` = leaves, which have no effect on falling nuts\n* ```|``` = tree trunk, which has no effect on falling nuts\n* ``` ``` = empty space, which has no effect on falling nuts\n\n# Kata Task\n\nShake the tree and count where the nuts land.\n\n**Output** - An array (same width as the tree) which indicates how many nuts fell at each position ^\n\n^ See the example tests\n\n# Notes\n\n* The nuts are always found at the top of the tree\n* Nuts do not affect the falling patterns of other nuts\n* There are always enough spaces for nuts to fall between branches\n* There are no branches at the extreme left/right edges of the tree matrix so it is not possible for a nut to fall \"out of bounds\"\n\n# Example\n\n<pre style='font-size:20px;line-height:22px;'>\n<span style='background:green'>.</span>o<span style='background:green'>.</span>oooooo<span style='background:green'>.</span>o<span style='background:green'>.</span>o<span style='background:green'>.</span>oooooo<span style='background:green'>.</span>\n<span style='background:green'>.</span><span style='background:green'>.</span>\\<span style='background:green'>.</span>\\<span style='background:green'>.</span><span style='background:green'>.</span><span style='background:green'>.</span>/<span style='background:green'>.</span><span style='background:green'>.</span>\\<span style='background:green'>.</span><span style='background:green'>.</span><span style='background:green'>.</span>/<span style='background:green'>.</span><span style='background:green'>.</span>\\<span style='background:green'>.</span><span style='background:green'>.</span>\n<span style='background:green'>.</span><span style='background:green'>.</span><span style='background:green'>.</span><span style='background:green'>.</span>/<span style='background:green'>.</span><span style='background:green'>.</span>\\<span style='background:green'>.</span><span style='background:green'>.</span><span style='background:green'>.</span><span style='background:green'>.</span>/<span style='background:green'>.</span><span style='background:green'>.</span><span style='background:green'>.</span><span style='background:green'>.</span><span style='background:green'>.</span><span style='background:green'>.</span>/<span style='background:green'>.</span>\n<span style='background:green'>.</span><span style='background:green'>.</span><span style='background:green'>.</span><span style='background:green'>.</span><span style='background:green'>.</span>\\<span style='background:green'>.</span><span style='background:green'>.</span><span style='background:green'>.</span><span style='background:green'>.</span>/<span style='background:green'>.</span>/<span style='background:green'>.</span>\\<span style='background:green'>.</span><span style='background:green'>.</span>\\<span style='background:green'>.</span>\\<span style='background:green'>.</span>\n<span style='background:green'>.</span><span style='background:green'>.</span><span style='background:green'>.</span><span style='background:green'>.</span><span style='background:green'>.</span>/<span style='background:green'>.</span><span style='background:green'>.</span>/<span style='background:green'>.</span>/<span style='background:green'>.</span>/<span style='background:green'>.</span><span style='background:green'>.</span><span style='background:green'>.</span>\\<span style='background:green'>.</span><span style='background:green'>.</span><span style='background:green'>.</span><span style='background:green'>.</span>\n<span style='background:green'>.</span><span style='background:green'>.</span><span style='background:green'>.</span>/<span style='background:green'>.</span><span style='background:green'>.</span><span style='background:green'>.</span>/<span style='background:green'>.</span><span style='background:green'>.</span>\\<span style='background:green'>.</span>/<span style='background:green'>.</span>\\<span style='background:green'>.</span><span style='background:green'>.</span>\\<span style='background:green'>.</span><span style='background:green'>.</span><span style='background:green'>.</span>\n<span style='background:green'>.</span>/<span style='background:green'>.</span><span style='background:green'>.</span><span style='background:green'>.</span><span style='background:green'>.</span><span style='background:green'>.</span><span style='background:green'>.</span><span style='background:green'>.</span>\\<span style='background:green'>.</span><span style='background:green'>.</span>/<span style='background:green'>.</span>\\<span style='background:green'>.</span><span style='background:green'>.</span>/<span style='background:green'>.</span><span style='background:green'>.</span><span style='background:green'>.</span>\n<span style='background:green'>.</span><span style='background:green'>.</span><span style='background:green'>.</span><span style='background:green'>.</span>\\<span style='background:green'>.</span><span style='background:green'>.</span><span style='background:green'>.</span><span style='background:green'>.</span>/<span style='background:green'>.</span><span style='background:green'>.</span><span style='background:green'>.</span><span style='background:green'>.</span><span style='background:green'>.</span>/<span style='background:green'>.</span>/<span style='background:green'>.</span><span style='background:green'>.</span><span style='background:green'>.</span>\n<span style='background:green'>.</span><span style='background:green'>.</span><span style='background:green'>.</span>/<span style='background:green'>.</span>\\<span style='background:green'>.</span>_<span style='background:green'>.</span>\\<span style='background:green'>.</span><span style='background:green'>.</span>/<span style='background:green'>.</span>_<span style='background:green'>.</span><span style='background:green'>.</span>/<span style='background:green'>.</span>\\<span style='background:green'>.</span>\n<span style='background:green'>.</span>\\<span style='background:green'>.</span><span style='background:green'>.</span><span style='background:green'>.</span><span style='background:green'>.</span>/<span style='background:green'>.</span>/<span style='background:green'>.</span><span style='background:green'>.</span><span style='background:green'>.</span><span style='background:green'>.</span>\\<span style='background:green'>.</span><span style='background:green'>.</span>/<span style='background:green'>.</span>\\<span style='background:green'>.</span><span style='background:green'>.</span>\n<span style='background:green'>.</span>/<span style='background:green'>.</span><span style='background:green'>.</span><span style='background:green'>.</span><span style='background:green'>.</span><span style='background:green'>.</span><span style='background:green'>.</span><span style='background:green'>.</span>/<span style='background:green'>.</span>/<span style='background:green'>.</span><span style='background:green'>.</span><span style='background:green'>.</span>/<span style='background:green'>.</span><span style='background:green'>.</span>/<span style='background:green'>.</span><span style='background:green'>.</span>\n         <span style='background:brown'> </span><span style='background:brown'> </span><span style='background:brown'> </span>\n         <span style='background:brown'> </span><span style='background:brown'> </span><span style='background:brown'> </span>\n         <span style='background:brown'> </span><span style='background:brown'> </span><span style='background:brown'> </span>\n         <span style='background:brown'> </span><span style='background:brown'> </span><span style='background:brown'> </span>\n         <span style='background:brown'> </span><span style='background:brown'> </span><span style='background:brown'> </span>\n         <span style='background:brown'> </span><span style='background:brown'> </span><span style='background:brown'> </span>\n101005000020000000040\n</pre>",
  "totalAttempts": 5215,
  "totalCompleted": 1242,
  "totalStars": 129,
  "voteScore": 291,
  "tags": [
    "Strings",
    "Algorithms"
  ],
  "contributorsWanted": true,
  "unresolved": {
    "issues": 2,
    "suggestions": 1
  }
}