{
  "id": "59884371d1d8d3d9270000a5",
  "name": "Nut Farm",
  "slug": "nut-farm",
  "category": "algorithms",
  "publishedAt": "2017-08-08T20:58:14.999Z",
  "approvedAt": "2017-08-10T07:31:27.180Z",
  "languages": [
    "java",
    "javascript",
    "csharp",
    "python",
    "dart",
    "lua"
  ],
  "url": "https://www.codewars.com/kata/59884371d1d8d3d9270000a5",
  "rank": {
    "id": -6,
    "name": "6 kyu",
    "color": "yellow"
  },
  "createdAt": "2017-08-07T10:39:45.162Z",
  "createdBy": {
    "username": "dinglemouse",
    "url": "https://www.codewars.com/users/dinglemouse"
  },
  "approvedBy": {
    "username": "Blind4Basics",
    "url": "https://www.codewars.com/users/Blind4Basics"
  },
  "totalAttempts": 5215,
  "totalCompleted": 1242,
  "totalStars": 129,
  "voteScore": 291,
  "tags": [
    "Strings",
    "Algorithms"
  ],
  "contributorsWanted": true,
  "unresolved": {
    "issues": 2,
    "suggestions": 1
  }
}