{
  "id": "599846fbc2bd3a62a4000031",
  "name": "Unique digit sequence II - Optimization problem",
  "slug": "unique-digit-sequence-ii-optimization-problem",
  "category": "refactoring",
  "publishedAt": "2017-08-20T10:34:13.538Z",
  "approvedAt": "2017-12-21T23:02:23.504Z",
  "languages": [
    "python"
  ],
  "url": "https://www.codewars.com/kata/599846fbc2bd3a62a4000031",
  "rank": {
    "id": -3,
    "name": "3 kyu",
    "color": "blue"
  },
  "createdAt": "2017-08-19T14:11:08.174Z",
  "createdBy": {
    "username": "Blind4Basics",
    "url": "https://www.codewars.com/users/Blind4Basics"
  },
  "approvedBy": {
    "username": "Bubbler",
    "url": "https://www.codewars.com/users/Bubbler"
  },
  "totalAttempts": 1269,
  "totalCompleted": 98,
  "totalStars": 55,
  "voteScore": 29,
  "tags": [
    "Memoization",
    "Refactoring",
    "Algorithms"
  ],
  "contributorsWanted": true,
  "unresolved": {
    "issues": 0,
    "suggestions": 0
  }
}