{
  "id": "5a97ee0a373c2ec6ee0000fb",
  "name": "BrainGolf: Clear Cells",
  "slug": "braingolf-clear-cells",
  "category": "games",
  "publishedAt": "2018-03-01T12:12:18.397Z",
  "approvedAt": "2018-03-01T15:01:47.706Z",
  "languages": [
    "bf"
  ],
  "url": "https://www.codewars.com/kata/5a97ee0a373c2ec6ee0000fb",
  "rank": {
    "id": -6,
    "name": "6 kyu",
    "color": "yellow"
  },
  "createdAt": "2018-03-01T12:12:00.454Z",
  "createdBy": {
    "username": "Unihedron",
    "url": "https://www.codewars.com/users/Unihedron"
  },
  "approvedBy": {
    "username": "Blind4Basics",
    "url": "https://www.codewars.com/users/Blind4Basics"
  },
  "totalAttempts": 509,
  "totalCompleted": 154,
  "totalStars": 4,
  "voteScore": 57,
  "tags": [
    "Restricted",
    "Puzzles"
  ],
  "contributorsWanted": true,
  "unresolved": {
    "issues": 0,
    "suggestions": 0
  }
}