{
  "id": "5ae786ad68e644e861000075",
  "name": "Cause str(x) to raise an exception",
  "slug": "cause-str-x-to-raise-an-exception",
  "category": "games",
  "publishedAt": "2018-05-01T12:19:13.231Z",
  "approvedAt": "2020-12-05T09:54:33.932Z",
  "languages": [
    "python"
  ],
  "url": "https://www.codewars.com/kata/5ae786ad68e644e861000075",
  "rank": {
    "id": -6,
    "name": "6 kyu",
    "color": "yellow"
  },
  "createdAt": "2018-04-30T21:12:14.058Z",
  "createdBy": {
    "username": "Chris_Rands",
    "url": "https://www.codewars.com/users/Chris_Rands"
  },
  "approvedBy": {
    "username": "user9644768",
    "url": "https://www.codewars.com/users/user9644768"
  },
  "totalAttempts": 5955,
  "totalCompleted": 171,
  "totalStars": 9,
  "voteScore": 59,
  "tags": [
    "Strings",
    "Puzzles"
  ],
  "contributorsWanted": true,
  "unresolved": {
    "issues": 1,
    "suggestions": 0
  }
}