{
  "id": "5c2fcbcba305ad2c4a91122d",
  "name": "(A+B)+C=A+(B+C)? Prove it!",
  "slug": "a-plus-b-plus-c-equals-a-plus-b-plus-c-prove-it",
  "category": "reference",
  "publishedAt": "2019-01-04T21:17:44.670Z",
  "approvedAt": "2019-01-06T02:19:09.915Z",
  "languages": [
    "haskell"
  ],
  "url": "https://www.codewars.com/kata/5c2fcbcba305ad2c4a91122d",
  "rank": {
    "id": -4,
    "name": "4 kyu",
    "color": "blue"
  },
  "createdAt": "2019-01-04T21:10:35.952Z",
  "createdBy": {
    "username": "ice1000",
    "url": "https://www.codewars.com/users/ice1000"
  },
  "approvedBy": {
    "username": "ZED.CWT",
    "url": "https://www.codewars.com/users/ZED.CWT"
  },
  "totalAttempts": 1120,
  "totalCompleted": 293,
  "totalStars": 34,
  "voteScore": 57,
  "tags": [
    "Theorem Proving",
    "Mathematics",
    "Fundamentals"
  ],
  "contributorsWanted": true,
  "unresolved": {
    "issues": 0,
    "suggestions": 0
  }
}