{
  "id": "5ea9b14c9b7bf50001b88e55",
  "name": "relating binary relations",
  "slug": "relating-binary-relations",
  "category": "games",
  "publishedAt": "2020-04-29T16:54:36.527Z",
  "approvedAt": "2020-05-01T04:14:31.969Z",
  "languages": [
    "lean",
    "coq"
  ],
  "url": "https://www.codewars.com/kata/5ea9b14c9b7bf50001b88e55",
  "rank": {
    "id": -7,
    "name": "7 kyu",
    "color": "white"
  },
  "createdAt": "2020-04-29T16:55:13.291Z",
  "createdBy": {
    "username": "kbuzzard",
    "url": "https://www.codewars.com/users/kbuzzard"
  },
  "approvedBy": {
    "username": "donaldsebleung",
    "url": "https://www.codewars.com/users/donaldsebleung"
  },
  "totalAttempts": 163,
  "totalCompleted": 89,
  "totalStars": 6,
  "voteScore": 27,
  "tags": [
    "Puzzles"
  ],
  "contributorsWanted": true,
  "unresolved": {
    "issues": 0,
    "suggestions": 0
  }
}