{
  "id": "62629041afc47200175bf2e6",
  "name": "Deep Lists",
  "slug": "deep-lists",
  "category": "reference",
  "publishedAt": "2022-04-22T11:25:22.399Z",
  "approvedAt": null,
  "languages": [
    "python"
  ],
  "url": "https://www.codewars.com/kata/62629041afc47200175bf2e6",
  "rank": {
    "id": null,
    "name": null,
    "color": null
  },
  "createdAt": "2022-04-22T11:23:45.304Z",
  "createdBy": {
    "username": "obidah",
    "url": "https://www.codewars.com/users/obidah"
  },
  "description": "you will be givin a number ```n = number of lists``` \n\n**Task :** create a function that creates ```n```  nested lists\n\n***Ex :***\n```python\nn = 5\n\noutput: [[[[[]]]]]\n\n```\n**Note :**\n\nif ```n <= 0``` return an empty list",
  "totalAttempts": 153,
  "totalCompleted": 67,
  "totalStars": 1,
  "voteScore": 47,
  "tags": [
    "Fundamentals"
  ],
  "contributorsWanted": true,
  "unresolved": {
    "issues": 0,
    "suggestions": 0
  }
}