{
  "id": "668b5761085d63da1ffa35d2",
  "name": "Kinetic Energy",
  "slug": "kinetic-energy",
  "category": "reference",
  "publishedAt": "2024-07-08T03:07:24.823Z",
  "approvedAt": null,
  "languages": [
    "python"
  ],
  "url": "https://www.codewars.com/kata/668b5761085d63da1ffa35d2",
  "rank": {
    "id": null,
    "name": null,
    "color": null
  },
  "createdAt": "2024-07-08T03:05:05.142Z",
  "createdBy": {
    "username": "sheluvsloona",
    "url": "https://www.codewars.com/users/sheluvsloona"
  },
  "totalAttempts": 10,
  "totalCompleted": 8,
  "totalStars": 0,
  "voteScore": -3,
  "tags": [
    "Mathematics"
  ],
  "contributorsWanted": true,
  "unresolved": {
    "issues": 1,
    "suggestions": 0
  }
}