{
  "id": "669f83634018e21b0fc2d706",
  "name": "ASCII Recamán's Sequence",
  "slug": "ascii-recamans-sequence",
  "category": "algorithms",
  "publishedAt": "2024-07-23T10:18:57.098Z",
  "approvedAt": null,
  "languages": [
    "python"
  ],
  "url": "https://www.codewars.com/kata/669f83634018e21b0fc2d706",
  "rank": {
    "id": null,
    "name": null,
    "color": null
  },
  "createdAt": "2024-07-23T10:18:11.205Z",
  "createdBy": {
    "username": "LuggiStruggi",
    "url": "https://www.codewars.com/users/LuggiStruggi"
  },
  "totalAttempts": 151,
  "totalCompleted": 6,
  "totalStars": 3,
  "voteScore": 4,
  "tags": [
    "ASCII Art",
    "Mathematics"
  ],
  "contributorsWanted": true,
  "unresolved": {
    "issues": 0,
    "suggestions": 0
  }
}