{
  "id": "538951ebdaea7dc4d2000293",
  "name": "Balance the tree",
  "slug": "balance-the-tree",
  "category": "algorithms",
  "publishedAt": "2014-05-31T03:52:11.480Z",
  "approvedAt": "2018-04-03T21:14:04.392Z",
  "languages": [
    "javascript"
  ],
  "url": "https://www.codewars.com/kata/538951ebdaea7dc4d2000293",
  "rank": {
    "id": -6,
    "name": "6 kyu",
    "color": "yellow"
  },
  "createdAt": "2014-05-31T03:52:12.728Z",
  "createdBy": {
    "username": "ykagan",
    "url": "https://www.codewars.com/users/ykagan"
  },
  "approvedBy": {
    "username": "JohanWiltink",
    "url": "https://www.codewars.com/users/JohanWiltink"
  },
  "totalAttempts": 2412,
  "totalCompleted": 142,
  "totalStars": 15,
  "voteScore": 60,
  "tags": [
    "Trees",
    "Data Structures",
    "Algorithms"
  ],
  "contributorsWanted": true,
  "unresolved": {
    "issues": 0,
    "suggestions": 0
  }
}