{
  "id": "53cce49fdf221844de0004bd",
  "name": "What adds up",
  "slug": "what-adds-up",
  "category": "algorithms",
  "publishedAt": "2014-07-21T13:15:44.547Z",
  "approvedAt": "2015-03-19T05:38:08.177Z",
  "languages": [
    "ruby",
    "python",
    "go"
  ],
  "url": "https://www.codewars.com/kata/53cce49fdf221844de0004bd",
  "rank": {
    "id": -6,
    "name": "6 kyu",
    "color": "yellow"
  },
  "createdAt": "2014-07-21T09:59:59.715Z",
  "createdBy": {
    "username": "kaffepanna",
    "url": "https://www.codewars.com/users/kaffepanna"
  },
  "approvedBy": {
    "username": "jhoffner",
    "url": "https://www.codewars.com/users/jhoffner"
  },
  "totalAttempts": 2484,
  "totalCompleted": 714,
  "totalStars": 24,
  "voteScore": 113,
  "tags": [
    "Arrays",
    "Searching",
    "Algorithms"
  ],
  "contributorsWanted": true,
  "unresolved": {
    "issues": 6,
    "suggestions": 3
  }
}