{
  "id": "549d55b1c36a0251ea000780",
  "name": "Prepare for the Easter!",
  "slug": "prepare-for-the-easter",
  "category": "reference",
  "publishedAt": "2014-12-26T19:16:24.915Z",
  "approvedAt": null,
  "languages": [
    "ruby",
    "javascript"
  ],
  "url": "https://www.codewars.com/kata/549d55b1c36a0251ea000780",
  "rank": {
    "id": null,
    "name": null,
    "color": null
  },
  "createdAt": "2014-12-26T12:33:53.742Z",
  "createdBy": {
    "username": "ozim",
    "url": "https://www.codewars.com/users/ozim"
  },
  "totalAttempts": 184,
  "totalCompleted": 37,
  "totalStars": 3,
  "voteScore": 11,
  "tags": [
    "Mathematics",
    "Algorithms",
    "Date Time",
    "Fundamentals"
  ],
  "contributorsWanted": true,
  "unresolved": {
    "issues": 1,
    "suggestions": 0
  }
}