{
  "id": "5710a8fd336aed00d9000594",
  "name": "Coding 3min : Remove screws II",
  "slug": "coding-3min-remove-screws-ii",
  "category": "games",
  "publishedAt": "2016-04-15T15:52:39.652Z",
  "approvedAt": "2018-01-03T09:18:14.317Z",
  "languages": [
    "javascript",
    "python"
  ],
  "url": "https://www.codewars.com/kata/5710a8fd336aed00d9000594",
  "rank": {
    "id": -5,
    "name": "5 kyu",
    "color": "yellow"
  },
  "createdAt": "2016-04-15T08:40:30.038Z",
  "createdBy": {
    "username": "myjinxin2015",
    "url": "https://www.codewars.com/users/myjinxin2015"
  },
  "approvedBy": {
    "username": "Voile",
    "url": "https://www.codewars.com/users/Voile"
  },
  "totalAttempts": 588,
  "totalCompleted": 81,
  "totalStars": 12,
  "voteScore": 32,
  "tags": [
    "Puzzles",
    "Games"
  ],
  "contributorsWanted": true,
  "unresolved": {
    "issues": 0,
    "suggestions": 0
  }
}