{
  "id": "5aca78023369fff1a400004a",
  "name": "Murder Most Foul",
  "slug": "murder-most-foul",
  "category": "bug_fixes",
  "publishedAt": "2018-04-09T14:42:31.528Z",
  "approvedAt": null,
  "languages": [
    "javascript"
  ],
  "url": "https://www.codewars.com/kata/5aca78023369fff1a400004a",
  "rank": {
    "id": null,
    "name": null,
    "color": null
  },
  "createdAt": "2018-04-08T20:13:54.847Z",
  "createdBy": {
    "username": "njons",
    "url": "https://www.codewars.com/users/njons"
  },
  "totalAttempts": 99,
  "totalCompleted": 26,
  "totalStars": 0,
  "voteScore": 1,
  "tags": [
    "Bugs"
  ],
  "contributorsWanted": false,
  "unresolved": {
    "issues": 1,
    "suggestions": 0
  }
}