{
  "id": "5af96cea3e9715ec670001dd",
  "name": "Projectile Motion",
  "slug": "projectile-motion",
  "category": "reference",
  "publishedAt": "2018-05-15T03:04:56.054Z",
  "approvedAt": "2018-05-19T02:51:27.409Z",
  "languages": [
    "ruby",
    "crystal",
    "python",
    "javascript",
    "coffeescript",
    "java",
    "scala",
    "typescript",
    "kotlin",
    "dart",
    "swift",
    "groovy",
    "csharp",
    "rust"
  ],
  "url": "https://www.codewars.com/kata/5af96cea3e9715ec670001dd",
  "rank": {
    "id": -6,
    "name": "6 kyu",
    "color": "yellow"
  },
  "createdAt": "2018-05-14T11:03:06.466Z",
  "createdBy": {
    "username": "narayanswa30663",
    "url": "https://www.codewars.com/users/narayanswa30663"
  },
  "approvedBy": {
    "username": "raulbc777",
    "url": "https://www.codewars.com/users/raulbc777"
  },
  "totalAttempts": 4061,
  "totalCompleted": 372,
  "totalStars": 52,
  "voteScore": 62,
  "tags": [
    "Fundamentals"
  ],
  "contributorsWanted": true,
  "unresolved": {
    "issues": 5,
    "suggestions": 2
  }
}